ArtexPing/__init__.py
ArtexPing/internet.py
ArtexPing-0.0.1.dist-info/LICENSE
ArtexPing-0.0.1.dist-info/METADATA
ArtexPing-0.0.1.dist-info/WHEEL
ArtexPing-0.0.1.dist-info/top_level.txt
ArtexPing-0.0.1.dist-info/RECORD
