Metadata-Version: 2.1
Name: ArtexPing
Version: 0.0.1
Summary: A python internet status checking library
Home-page: https://github.com/JunaidParkar/Python-Check_internet_status/
Author: Artex AI
Project-URL: Documentation, https://github.com/JunaidParkar/Python-Check_internet_status/
Project-URL: Source, https://github.com/JunaidParkar/Python-Check_internet_status/
Project-URL: Tracker, https://github.com/JunaidParkar/Python-Check_internet_status/
Classifier: Programming Language :: Python :: 3
Classifier: License :: OSI Approved :: Boost Software License 1.0 (BSL-1.0)
Classifier: Operating System :: OS Independent
Requires-Python: >=3.6
License-File: LICENSE
Requires-Dist: requests ==2.32.3
